rake/__init__.py
rake/__main__.py
rake/core.py
rake/temp/__init__.py
rake/utils/__init__.py
rake/utils/helpers.py
rake/utils/keypath.py
rake/utils/notation.py
rake_python-0.1.11.dist-info/LICENSE
rake_python-0.1.11.dist-info/METADATA
rake_python-0.1.11.dist-info/WHEEL
rake_python-0.1.11.dist-info/entry_points.txt
rake_python-0.1.11.dist-info/top_level.txt
rake_python-0.1.11.dist-info/RECORD
