Metadata-Version: 2.1
Name: rake-python
Version: 0.1.11
Summary: Rake is a simple yet powerful web scraping tool that allows you to configure and execute complex and repetitive scraping tasks with ease and little to no code.
Home-page: https://github.com/eddiedane/rake
Author: Eddie Dane
Classifier: Development Status :: 4 - Beta
Classifier: Intended Audience :: Developers
Classifier: Topic :: Software Development :: Libraries :: Python Modules
Classifier: Programming Language :: Python :: 3
Classifier: Programming Language :: Python :: 3.6
Classifier: Programming Language :: Python :: 3.7
Classifier: Programming Language :: Python :: 3.8
Classifier: Programming Language :: Python :: 3.9
Classifier: Programming Language :: Python :: 3.10
Classifier: Programming Language :: Python :: 3.11
Classifier: Programming Language :: Python :: 3.12
Classifier: License :: OSI Approved :: MIT License
Classifier: Operating System :: OS Independent
Requires-Python: >=3.6
License-File: LICENSE
Requires-Dist: PyYAML
Requires-Dist: pandas
Requires-Dist: playwright
Requires-Dist: colorama
Requires-Dist: tabulate
Requires-Dist: python-slugify
Requires-Dist: click
Requires-Dist: openpyxl
Requires-Dist: pypandoc
